ne_ver-3.1.2.data/scripts/never
never/__init__.py
never/lib.py
never/next.py
ne_ver-3.1.2.dist-info/LICENSE
ne_ver-3.1.2.dist-info/METADATA
ne_ver-3.1.2.dist-info/WHEEL
ne_ver-3.1.2.dist-info/top_level.txt
ne_ver-3.1.2.dist-info/RECORD
