Metadata-Version: 2.1
Name: ne-ver
Version: 3.1.2
Summary: Never == Next Version
Home-page: https://github.com/swesterveld/next
Author: Sil Westerveld
Author-email: dev+never@silwesterveld.com
License: UNKNOWN
Project-URL: Bug Tracker, https://github.com/swesterveld/next/issues
Platform: UNKNOWN
Classifier: Development Status :: 4 - Beta
Classifier: Environment :: Console
Classifier: Intended Audience :: Developers
Classifier: Intended Audience :: System Administrators
Classifier: License :: OSI Approved :: MIT License
Classifier: Natural Language :: English
Classifier: Operating System :: OS Independent
Classifier: Programming Language :: Python :: 3
Classifier: Topic :: Software Development
Classifier: Topic :: System :: Software Distribution
Classifier: Topic :: Utilities
Classifier: Typing :: Typed
Requires-Python: >=3.9
License-File: LICENSE
Requires-Dist: gitpython
Requires-Dist: python-dotenv
Requires-Dist: requests
